setup.py
buzzfizz/__init__.py
buzzfizz/__main__.py
buzzfizz/fibonacci_buzzfizz.py
buzzfizz.egg-info/PKG-INFO
buzzfizz.egg-info/SOURCES.txt
buzzfizz.egg-info/dependency_links.txt
buzzfizz.egg-info/not-zip-safe
buzzfizz.egg-info/top_level.txt