Metadata-Version: 1.0
Name: buzzfizz
Version: 0.3
Summary: Sample BuzzFuzz program used for screening
Home-page: https://github.com/m1kelyons/buzzfizz
Author: Mike Lyons
Author-email: UNKNOWN
License: MIT
Platform: UNKNOWN
